LICENSE
MANIFEST.in
README.md
pyproject.toml
setup.cfg
setup.py
html_renderer/package-lock.json
html_renderer/package.json
html_renderer/vue.config.js
html_renderer/public/index.html
html_renderer/public/sample.json
html_renderer/src/App.vue
html_renderer/src/Frame.vue
html_renderer/src/Header.vue
html_renderer/src/appState.js
html_renderer/src/main.js
html_renderer/src/assets/favicon.png
html_renderer/src/model/Frame.js
html_renderer/src/model/Group.js
joulehunter/__init__.py
joulehunter/__main__.py
joulehunter/energy.py
joulehunter/frame.py
joulehunter/middleware.py
joulehunter/processors.py
joulehunter/profiler.py
joulehunter/session.py
joulehunter/stack_sampler.py
joulehunter/typing.py
joulehunter/util.py
joulehunter.egg-info/PKG-INFO
joulehunter.egg-info/SOURCES.txt
joulehunter.egg-info/dependency_links.txt
joulehunter.egg-info/entry_points.txt
joulehunter.egg-info/not-zip-safe
joulehunter.egg-info/top_level.txt
joulehunter/low_level/stat_profile.c
joulehunter/renderers/__init__.py
joulehunter/renderers/base.py
joulehunter/renderers/console.py
joulehunter/renderers/html.py
joulehunter/renderers/jsonrenderer.py
joulehunter/renderers/html_resources/app.js
joulehunter/vendor/__init__.py
joulehunter/vendor/appdirs.py
joulehunter/vendor/decorator.py
test/__init__.py
test/conftest.py
test/fake_time_util.py
test/test_cmdline.py
test/test_overflow.py
test/test_processors.py
test/test_profiler.py
test/test_profiler_async.py
test/test_stack_sampler.py
test/test_threading.py
test/util.py
test/low_level/__init__.py
test/low_level/test_context.py
test/low_level/test_custom_timer.py
test/low_level/test_setstatprofile.py
test/low_level/test_threaded.py
test/low_level/util.py