Metadata-Version: 2.1
Name: joulehunter
Version: 1.0
Summary: detect where your code consumes energy the most so you can optimize those functions
Home-page: https://github.com/powerapi-ng/joulehunter
Author: chakib belgaid
Author-email: chakib.belgaid@gmail.com
License: UNKNOWN
Project-URL: Bug Tracker, https://github.com/powerapi-ng/joulehunter/issues
Keywords: profiling,profile,profiler,energy,cpu,time,sampling
Platform: UNKNOWN
Classifier: Environment :: Console
Classifier: Environment :: Web Environment
Classifier: Intended Audience :: Developers
Classifier: License :: OSI Approved :: BSD License
Classifier: Operating System :: POSIX
Classifier: Topic :: Software Development :: Debuggers
Classifier: Topic :: Software Development :: Testing
Requires-Python: >=3.7
